.gitignore
README.md
requirements.txt
setup.py
docs/Makefile
docs/source/addons.rst
docs/source/conf.py
docs/source/core.rst
docs/source/db.rst
docs/source/example.rst
docs/source/index.rst
docs/source/microserver.addons.rst
docs/source/microserver.addons.siege.rst
docs/source/microserver.addons.swagger.management.commands.rst
docs/source/microserver.addons.swagger.management.rst
docs/source/microserver.addons.swagger.rst
docs/source/microserver.addons.user.rst
docs/source/microserver.cache.rst
docs/source/microserver.conf.rst
docs/source/microserver.core.handlers.rst
docs/source/microserver.core.management.commands.rst
docs/source/microserver.core.management.rst
docs/source/microserver.core.rst
docs/source/microserver.db.rst
docs/source/microserver.files.rst
docs/source/microserver.libs.rst
docs/source/microserver.mail.rst
docs/source/microserver.rst
docs/source/microserver.tests.rst
docs/source/microserver.tests.settings.rst
docs/source/microserver.utils.rst
docs/source/microserver.validators.rst
docs/source/modules.rst
microserver/__init__.py
microserver/addons/__init__.py
microserver/addons/checkcode/__init__.py
microserver/addons/checkcode/handlers.py
microserver/addons/checkcode/models.py
microserver/addons/command/__init__.py
microserver/addons/command/handlers.py
microserver/addons/deploy/__init__.py
microserver/addons/logentry/__init__.py
microserver/addons/logentry/models.py
microserver/addons/siege/__init__.py
microserver/addons/siege/handlers.py
microserver/addons/siege/requirements.txt
microserver/addons/smsauth/__init__.py
microserver/addons/smsauth/handlers.py
microserver/addons/smsauth/models.py
microserver/addons/swagger/__init__.py
microserver/addons/swagger/api.py
microserver/addons/swagger/handlers.py
microserver/addons/swagger/template_loader.py
microserver/addons/swagger/management/__init__.py
microserver/addons/swagger/management/commands/__init__.py
microserver/addons/swagger/management/commands/create_apidoc.py
pymicroserver.egg-info/PKG-INFO
pymicroserver.egg-info/SOURCES.txt
pymicroserver.egg-info/dependency_links.txt
pymicroserver.egg-info/top_level.txt