Metadata-Version: 1.0
Name: pymicroserver
Version: 2.0.39
Summary: A web application framework base on tornado and other async libraries.
Home-page: http://www.niyoufa.com
Author: niyoufa
Author-email: niyoufa@aegis-data.cn
License: BSD
Platform: UNKNOWN
